netbox_aws_vpc_plugin/__init__.py
netbox_aws_vpc_plugin/choices.py
netbox_aws_vpc_plugin/constants.py
netbox_aws_vpc_plugin/filtersets.py
netbox_aws_vpc_plugin/forms.py
netbox_aws_vpc_plugin/navigation.py
netbox_aws_vpc_plugin/search.py
netbox_aws_vpc_plugin/tables.py
netbox_aws_vpc_plugin/urls.py
netbox_aws_vpc_plugin/views.py
netbox_aws_vpc_plugin/api/__init__.py
netbox_aws_vpc_plugin/api/nested_serializers.py
netbox_aws_vpc_plugin/api/serializers.py
netbox_aws_vpc_plugin/api/urls.py
netbox_aws_vpc_plugin/api/views.py
netbox_aws_vpc_plugin/graphql/__init__.py
netbox_aws_vpc_plugin/graphql/filters.py
netbox_aws_vpc_plugin/graphql/schema.py
netbox_aws_vpc_plugin/graphql/types.py
netbox_aws_vpc_plugin/migrations/0001_initial.py
netbox_aws_vpc_plugin/migrations/0002_awsaccount_tenant_awssubnet_region_awsvpc_region.py
netbox_aws_vpc_plugin/migrations/0003_awsaccount_status_awssubnet_status_awsvpc_status.py
netbox_aws_vpc_plugin/migrations/0004_awssubnet_subnet_ipv6_cidr_and_more.py
netbox_aws_vpc_plugin/migrations/0005_awsvpc_vpc_ipv6_cidrs_and_more.py
netbox_aws_vpc_plugin/migrations/__init__.py
netbox_aws_vpc_plugin/models/__init__.py
netbox_aws_vpc_plugin/models/aws_account.py
netbox_aws_vpc_plugin/models/aws_subnet.py
netbox_aws_vpc_plugin/models/aws_vpc.py
netbox_aws_vpc_plugin/templates/netbox_aws_vpc_plugin/awsaccount.html
netbox_aws_vpc_plugin/templates/netbox_aws_vpc_plugin/awssubnet.html
netbox_aws_vpc_plugin/templates/netbox_aws_vpc_plugin/awsvpc.html
netbox_aws_vpc_plugin-0.1.0.dist-info/licenses/LICENSE
netbox_aws_vpc_plugin-0.1.0.dist-info/METADATA
netbox_aws_vpc_plugin-0.1.0.dist-info/WHEEL
netbox_aws_vpc_plugin-0.1.0.dist-info/top_level.txt
netbox_aws_vpc_plugin-0.1.0.dist-info/RECORD
