Metadata-Version: 2.4
Name: netbox-aws-vpc-plugin
Version: 0.1.0
Summary: NetBox plugin for modeling AWS VPCs in NetBox
Author-email: Daniel MacLaury <daniel@danielmaclaury.com>
License-Expression: Apache-2.0
Project-URL: Documentation, https://github.com/dmaclaury/netbox-aws-vpc-plugin/blob/main/README.md
Project-URL: Source, https://github.com/dmaclaury/netbox-aws-vpc-plugin
Project-URL: Tracker, https://github.com/dmaclaury/netbox-aws-vpc-plugin/issues
Classifier: Development Status :: 3 - Alpha
Classifier: Intended Audience :: Developers
Classifier: Natural Language :: English
Classifier: Programming Language :: Python :: 3 :: Only
Classifier: Programming Language :: Python :: 3.12
Classifier: Programming Language :: Python :: 3.13
Classifier: Programming Language :: Python :: 3.14
Requires-Python: >=3.12.0
License-File: LICENSE
Provides-Extra: test
Requires-Dist: black==25.12.0; extra == "test"
Requires-Dist: check-manifest==0.51; extra == "test"
Requires-Dist: flake8; extra == "test"
Requires-Dist: flake8-pyproject; extra == "test"
Requires-Dist: pre-commit==4.5.1; extra == "test"
Requires-Dist: pytest==9.0.2; extra == "test"
Dynamic: license-file
